zephyr/__init__.py
zephyr/common/__init__.py
zephyr/common/zephyr_session.py
zephyr/common/cloud/__init__.py
zephyr/common/cloud/zephyr_cloud_session.py
zephyr/common/cloud/endpoints/__init__.py
zephyr/common/cloud/endpoints/endpoints.py
zephyr/common/cloud/endpoints/paths.py
zephyr/scale/__init__.py
zephyr/scale/scale.py
zephyr/scale/cloud/__init__.py
zephyr/scale/cloud/cloud_api.py
zephyr/scale/cloud/endpoints/__init__.py
zephyr/scale/cloud/endpoints/endpoints.py
zephyr/scale/cloud/endpoints/paths.py
zephyr/scale/server/__init__.py
zephyr/scale/server/server_api.py
zephyr/scale/server/server_defaults.py
zephyr/scale/server/endpoints/__init__.py
zephyr/scale/server/endpoints/endpoints.py
zephyr/scale/server/endpoints/paths.py
zephyr/squad/__init__.py
zephyr/squad/squad.py
zephyr/squad/zephyr_squad_session.py
zephyr/squad/cloud/__init__.py
zephyr/squad/cloud/cloud_api.py
zephyr/squad/server/__init__.py
zephyr/squad/server/actions.py
zephyr/squad/server/server_api.py
zephyr/squad/server/endpoints/__init__.py
zephyr/squad/server/endpoints/actions.py
zephyr/squad/server/endpoints/endpoints.py
zephyr/squad/server/endpoints/paths.py
zephyr/utils/__init__.py
zephyr/utils/common.py
zephyr_test_management-0.2.1.dist-info/LICENSE
zephyr_test_management-0.2.1.dist-info/METADATA
zephyr_test_management-0.2.1.dist-info/WHEEL
zephyr_test_management-0.2.1.dist-info/top_level.txt
zephyr_test_management-0.2.1.dist-info/RECORD
