Metadata-Version: 2.1
Name: zephyr-test-management
Version: 0.2.1
Summary: Wrappers for both Zephyr Scale and Zephyr Squad (TM4J) REST APIs
Home-page: https://github.com/Steinhagen/zephyr-test-management
Author: Viorel-Catalin Rapiteanu
Author-email: catalin.rapiteanu@gmail.com
Project-URL: Bug Tracker, https://github.com/Steinhagen/zephyr-test-management/issues
Classifier: Programming Language :: Python :: 3.6
Classifier: Programming Language :: Python :: 3.7
Classifier: Programming Language :: Python :: 3.8
Classifier: Programming Language :: Python :: 3.9
Classifier: Programming Language :: Python :: 3.10
Classifier: Programming Language :: Python :: 3.11
Classifier: Programming Language :: Python :: 3.12
Classifier: Programming Language :: Python :: 3.13
Classifier: License :: OSI Approved :: Apache Software License
Classifier: Operating System :: OS Independent
Requires-Python: >=3.6
License-File: LICENSE
Requires-Dist: requests
